setup.py
streamplot.py
streamplot.egg-info/PKG-INFO
streamplot.egg-info/SOURCES.txt
streamplot.egg-info/dependency_links.txt
streamplot.egg-info/not-zip-safe
streamplot.egg-info/requires.txt
streamplot.egg-info/top_level.txt