Metadata-Version: 1.0
Name: streamplot
Version: 1.0
Summary: Real Time Plots with pyqtgraph
Home-page: https://github.com/GuillaumeGenthial/streamplot/tarball/1.0
Author: Guillaume Genthial
Author-email: genthial@stanford.edu
License: MIT
Platform: UNKNOWN
